defaultmod/__init__.py
defaultmodwerrors/__init__.py
defaultmod-1.0.2.dist-info/METADATA
defaultmod-1.0.2.dist-info/WHEEL
defaultmod-1.0.2.dist-info/top_level.txt
defaultmod-1.0.2.dist-info/RECORD
